Metadata-Version: 1.0
Name: distributions-nd-mestevam
Version: 0.2
Summary: Gaussian distributions
Home-page: UNKNOWN
Author: Marcelo Estevam
Author-email: UNKNOWN
License: UNKNOWN
Platform: UNKNOWN
